{
    "dataset": "cifar10",
    "results": {
        "Step 200": [
            10.14,
            10.0,
            12.4,
            16.85,
            19.05,
            27.27,
            33.67,
            35.35,
            34.89,
            35.95,
            35.69,
            37.11,
            43.54,
            44.18,
            44.79,
            47.71,
            49.09,
            49.28,
            50.22,
            50.91,
            51.44,
            52.73,
            51.78,
            53.36,
            52.05,
            52.83,
            53.83,
            54.8,
            54.62,
            53.53,
            54.99,
            55.44,
            54.12,
            54.37,
            54.36,
            56.09,
            55.43,
            54.14,
            56.16,
            55.19,
            55.45,
            56.68,
            55.67,
            55.86,
            55.0,
            55.18,
            55.91,
            56.61,
            55.54,
            55.72
        ],
        "Step 500": [
            9.88,
            16.22,
            22.83,
            27.74,
            31.42,
            34.26,
            36.45,
            37.02,
            40.95,
            42.07,
            42.79,
            45.23,
            47.88,
            48.56,
            50.35,
            49.89,
            49.65,
            50.32,
            50.97,
            50.8,
            53.25,
            53.01,
            51.68,
            50.88,
            53.14,
            52.28,
            53.83,
            54.87,
            54.89,
            54.63,
            53.7,
            54.12,
            55.34,
            54.93,
            54.6,
            56.6,
            55.67,
            56.01,
            55.35,
            53.93,
            53.82,
            56.56,
            56.23,
            54.81,
            54.8,
            55.41,
            54.87,
            55.42,
            57.34,
            54.52
        ],
        "Step 700": [
            9.82,
            15.58,
            17.03,
            22.83,
            30.62,
            36.47,
            38.39,
            37.4,
            39.53,
            38.11,
            42.61,
            43.3,
            45.43,
            43.43,
            48.66,
            49.26,
            49.98,
            52.73,
            53.8,
            52.17,
            53.44,
            52.95,
            54.58,
            53.94,
            54.79,
            56.06,
            53.16,
            54.97,
            55.8,
            55.46,
            56.95,
            56.05,
            55.11,
            56.16,
            54.01,
            56.24,
            56.77,
            58.49,
            55.62,
            58.51,
            56.27,
            56.59,
            58.22,
            57.5,
            56.72,
            58.47,
            58.23,
            58.26,
            58.84,
            57.38
        ],
        "Step 1000": [
            10.0,
            12.05,
            17.43,
            23.16,
            27.69,
            31.63,
            33.17,
            34.97,
            35.75,
            36.37,
            41.03,
            40.05,
            42.32,
            45.26,
            45.3,
            45.59,
            44.78,
            46.25,
            47.02,
            48.82,
            48.67,
            51.15,
            51.3,
            51.97,
            52.39,
            52.93,
            51.16,
            52.7,
            53.44,
            51.94,
            52.83,
            53.74,
            53.25,
            53.73,
            54.14,
            55.82,
            56.41,
            55.4,
            53.52,
            56.31,
            56.09,
            56.68,
            56.4,
            56.06,
            55.45,
            57.69,
            57.06,
            55.77,
            57.55,
            57.47
        ]
    },
    "steps": [
        200,
        500,
        700,
        1000
    ],
    "args": {
        "steps": [
            200,
            500,
            700,
            1000
        ],
        "weights_dir": "/data/ccy/fedproto/20260103_082205/weights",
        "dataset": "cifar10",
        "model": "cnn",
        "data_dir": "/data/ccy/datasets",
        "num_users": 10,
        "batch_size": 256,
        "synthesis_batch_size": 256,
        "distill_epochs": 50,
        "lr": 0.01,
        "momentum": 0.9,
        "lr_g": 0.001,
        "optimizer": "sgd",
        "weight_decay": 0.0,
        "seed": 3407,
        "adv": 1,
        "bn": 1,
        "oh": 1,
        "act": 0,
        "g_steps": 20,
        "T": 20,
        "beta": 0.5,
        "partition": "dirichlet"
    }
}